reprod/__init__.py
reprod/gpt2_jax/__init__.py
reprod/gpt2_jax/config.py
reprod/gpt2_jax/main.py
reprod/gpt2_jax/model.py
reprod/gpt2_jax/sample.py
reprod/gpt2_jax/train.py
reprod/gpt2_jax/utils.py
reprod/gpt2_numpy/__init__.py
reprod/gpt2_numpy/config.py
reprod/gpt2_numpy/modeling_np.py
reprod/gpt2_numpy/sample.py
reprod/gpt2_numpy/utils.py
reprod-0.1.2.dist-info/LICENSE
reprod-0.1.2.dist-info/METADATA
reprod-0.1.2.dist-info/WHEEL
reprod-0.1.2.dist-info/top_level.txt
reprod-0.1.2.dist-info/RECORD
