Metadata-Version: 2.1
Name: reprod
Version: 0.1.2
Summary: Reproduce important work in machine learning
Author-email: Yadong Wen <yadongwen+reprod@gmail.com>
License: MIT License
Keywords: machine-learning,deep-learning
Requires-Python: ~=3.9
License-File: LICENSE
